gx/__init__.py
gx/globals.py
gx/gpu.py
gx/main.py
gx/notify.py
gx/occupier.py
gx/settings.py
gx_cli-0.1.4.dist-info/METADATA
gx_cli-0.1.4.dist-info/WHEEL
gx_cli-0.1.4.dist-info/entry_points.txt
gx_cli-0.1.4.dist-info/licenses/LICENSE
gx_cli-0.1.4.dist-info/RECORD
