Metadata-Version: 2.4
Name: gx-cli
Version: 0.1.4
Summary: A simple CLI tool that runs your commands once GPUs are available.
Project-URL: Homepage, https://github.com/helium777/gx
Project-URL: Bug Tracker, https://github.com/helium777/gx/issues
Author-email: Helium7 <helium747@gmail.com>
License: MIT
License-File: LICENSE
Classifier: Development Status :: 3 - Alpha
Classifier: Environment :: Console
Classifier: Intended Audience :: Developers
Classifier: License :: OSI Approved :: MIT License
Classifier: Operating System :: POSIX :: Linux
Classifier: Programming Language :: Python :: 3
Classifier: Programming Language :: Python :: 3 :: Only
Classifier: Programming Language :: Python :: 3.11
Classifier: Programming Language :: Python :: 3.12
Classifier: Topic :: System :: Monitoring
Classifier: Topic :: Utilities
Requires-Python: >=3.11
Requires-Dist: click>=8.1.8
Requires-Dist: humanize>=4.12.2
Requires-Dist: nvidia-ml-py>=12.570.86
Requires-Dist: pydantic-settings>=2.8.1
Requires-Dist: requests>=2.32.3
Requires-Dist: rich>=13.9.4
Requires-Dist: tomli-w>=1.2.0
Provides-Extra: occupy
Requires-Dist: numba>=0.60.0; extra == 'occupy'
Requires-Dist: numpy>=2.0.2; extra == 'occupy'
Requires-Dist: setproctitle>=1.3.5; extra == 'occupy'
